freetype_supp/__init__.py
freetype_supp/enum.py
freetype_supp/get_truetype_engine_type.py
freetype_supp/load_sfnt_table.py
freetype_supp/open_face.py
freetype_supp-0.0.4.dist-info/licenses/LICENSE
freetype_supp-0.0.4.dist-info/METADATA
freetype_supp-0.0.4.dist-info/WHEEL
freetype_supp-0.0.4.dist-info/top_level.txt
freetype_supp-0.0.4.dist-info/RECORD
